[
  {
    "id": "00e76754-294a-456d-935b-679cd532d26b",
    "date": "4/5/2025",
    "venue": "Riverbillies",
    "city": "Gibraltar",
    "state": "MI",
    "startTime": "8:00 PM",
    "endTime": "11:00 PM",
    "isPrivate": false,
    "eventLink": "https://www.facebook.com/events/924832226460696/",
    "clientId": "c1f8e6d0-4a2b-4c5d-8e9f-1a2b3c4d5e6f"
  },
  {
    "id": "0758e385-8544-48b9-98c4-a2d78c0bb700",
    "date": "5/9/2025",
    "venue": "Sandbar Grille",
    "city": "LaSalle",
    "state": "MI",
    "startTime": "8:30 PM",
    "endTime": "11:59 PM",
    "isPrivate": false,
    "eventLink": "https://www.facebook.com/events/3785871661726015/",
    "clientId": "a2b3c4d5-5e6f-4a7b-9c8d-2e3f4a5b6c7d"
  },
  {
    "id": "5c772b8b-a5c9-44cd-8d1c-69a0f388cbe0",
    "date": "5/30/2025",
    "venue": "Riverbillies",
    "city": "Gibraltar",
    "state": "MI",
    "startTime": "8:00 PM",
    "endTime": "11:00 PM",
    "isPrivate": false,
    "eventLink": "https://www.facebook.com/events/648999594954174/",
    "clientId": "c1f8e6d0-4a2b-4c5d-8e9f-1a2b3c4d5e6f"
  },
  {
    "id": "ee979544-5c9b-4b2e-bd67-db8a2a7aaf68",
    "date": "6/20/2025",
    "venue": "Riverbillies",
    "city": "Gibraltar",
    "state": "MI",
    "startTime": "8:00 PM",
    "endTime": "11:00 PM",
    "isPrivate": false,
    "eventLink": "https://www.facebook.com/events/1347115766617472/",
    "clientId": "c1f8e6d0-4a2b-4c5d-8e9f-1a2b3c4d5e6f"
  },
  {
    "id": "b673aee3-d9b2-4cf8-8d8b-2ac2106862bd",
    "date": "6/21/2025",
    "venue": "Sandbar Grille",
    "city": "LaSalle",
    "state": "MI",
    "startTime": "8:30 PM",
    "endTime": "11:59 PM",
    "isPrivate": false,
    "eventLink": "https://www.facebook.com/events/731665099543941/",
    "clientId": "a2b3c4d5-5e6f-4a7b-9c8d-2e3f4a5b6c7d"
  },
  {
    "id": "57802589-5dd8-4896-8630-125aa6f515cc",
    "date": "7/12/2025",
    "venue": "Original Gravity",
    "city": "Milan",
    "state": "MI",
    "startTime": "4:00 PM",
    "endTime": "6:00 PM",
    "isPrivate": false,
    "eventLink": "https://fb.me/e/4vYE3YLKv",
    "clientId": "b3c4d5e6-6f7a-4b8c-0d9e-3f4a5b6c7d8e"
  },
  {
    "id": "bd5ee01b-cbf4-4fcb-9e67-42257ef91537",
    "date": "7/19/2025",
    "venue": "Timothy Graduation Party @ VFW Brownstown",
    "city": "Brownstown",
    "state": "MI",
    "startTime": "4:00 PM",
    "endTime": "6:00 PM",
    "isPrivate": true,
    "eventLink": "",
    "clientId": "e2f3a4b5-5c6d-4e7f-9a8b-2c3d4e5f6a7b"
  },
  {
    "id": "f62eddf0-8261-4225-be9a-122b92a0c905",
    "date": "8/1/2025",
    "venue": "Riverbillies",
    "city": "Gibraltar",
    "state": "MI",
    "startTime": "8:00 PM",
    "endTime": "11:00 PM",
    "isPrivate": false,
    "eventLink": "https://fb.me/e/4jcoAc8Sx",
    "clientId": "c1f8e6d0-4a2b-4c5d-8e9f-1a2b3c4d5e6f"
  },
  {
    "id": "afe19d05-a77d-4517-83a2-ae7eabe0cea8",
    "date": "8/23/2025",
    "venue": "Riverbillies",
    "city": "Gibraltar",
    "state": "MI",
    "startTime": "8:00 PM",
    "endTime": "11:00 PM",
    "isPrivate": false,
    "eventLink": "https://fb.me/e/9HR8VqORv",
    "clientId": "c1f8e6d0-4a2b-4c5d-8e9f-1a2b3c4d5e6f"
  },
  {
    "id": "074c8dc1-9aaf-4398-8b60-fc0599678fc2",
    "date": "9/12/2025",
    "venue": "FEDCO",
    "city": "Monroe",
    "state": "MI",
    "startTime": "8:30 PM",
    "endTime": "6:00 PM",
    "isPrivate": true,
    "eventLink": "",
    "clientId": "d5e6f7a8-8b9c-4d0e-2f1a-5b6c7d8e9f0a"
  },
  {
    "id": "0cac0aa5-e882-410f-826d-f6a99d21063e",
    "date": "9/13/2025",
    "venue": "Sandbar Grille",
    "city": "LaSalle",
    "state": "MI",
    "startTime": "8:30 PM",
    "endTime": "11:59 PM",
    "isPrivate": false,
    "eventLink": "https://fb.me/e/4kGrMlpwI",
    "clientId": "a2b3c4d5-5e6f-4a7b-9c8d-2e3f4a5b6c7d"
  },
  {
    "id": "ae3f5641-02f6-476d-b28a-b0ffcc27057a",
    "date": "9/19/2025",
    "venue": "Romulus Pumpkin Fest",
    "city": "Romulus",
    "state": "MI",
    "startTime": "6:00 PM",
    "endTime": "8:00 PM",
    "isPrivate": false,
    "eventLink": "https://fb.me/e/8rqiPIxqJ",
    "clientId": "e6f7a8b9-9c0d-4e1f-3a2b-6c7d8e9f0a1b"
  },
  {
    "id": "c35693f6-831f-46ce-9b86-0f1b0bd13f85",
    "date": "10/17/2025",
    "venue": "Hell Saloon",
    "city": "Hell",
    "state": "MI",
    "startTime": "8:00 PM",
    "endTime": "11:59 PM",
    "isPrivate": false,
    "eventLink": "https://fb.me/e/5Pvu2XkIP",
    "clientId": "f7a8b9c0-0d1e-4f2a-4b3c-7d8e9f0a1b2c"
  },
  {
    "id": "4abe090c-4f40-491d-b792-9447a50af432",
    "date": "10/24/2025",
    "venue": "Riverbillies",
    "city": "Gibraltar",
    "state": "MI",
    "startTime": "8:00 PM",
    "endTime": "11:00 PM",
    "isPrivate": false,
    "eventLink": "https://fb.me/e/4O38uYBcy",
    "clientId": "c1f8e6d0-4a2b-4c5d-8e9f-1a2b3c4d5e6f"
  },
  {
    "id": "751ee030-b22b-4e10-8bfe-709432ec6e32",
    "date": "11/28/2025",
    "venue": "Hell Saloon",
    "city": "Hell",
    "state": "MI",
    "startTime": "8:00 PM",
    "endTime": "11:59 PM",
    "isPrivate": false,
    "eventLink": "https://fb.me/e/8EFLWLk4v",
    "clientId": "f7a8b9c0-0d1e-4f2a-4b3c-7d8e9f0a1b2c"
  },
  {
    "id": "fcf5a67a-641f-4198-83da-0747cc5ae025",
    "date": "12/12/2025",
    "venue": "Hell Saloon",
    "city": "Hell",
    "state": "MI",
    "startTime": "8:00 PM",
    "endTime": "11:59 PM",
    "isPrivate": false,
    "eventLink": "https://fb.me/e/38NuvVM0w",
    "clientId": "f7a8b9c0-0d1e-4f2a-4b3c-7d8e9f0a1b2c"
  },
  {
    "id": "c7dbfff1-cc25-406a-8cf4-6d35165f3108",
    "date": "12/31/2025",
    "venue": "Action Detroit",
    "city": "Romulus",
    "state": "MI",
    "startTime": "9:00 PM",
    "endTime": "11:59 PM",
    "isPrivate": false,
    "personnel": [
      "David",
      "Shelley",
      "Tom",
      "Lester",
      "Anthony"
    ],
    "eventLink": "https://www.facebook.com/events/1237030125141573/",
    "clientId": "a8b9c0d1-1e2f-4a3b-5c4d-8e9f0a1b2c3d"
  },
  {
    "id": "60e1f655-ef4b-49aa-a4f0-faad9d2d674b",
    "date": "1/17/2026",
    "venue": "Riverbillies",
    "city": "Gibraltar",
    "state": "MI",
    "startTime": "8:00 PM",
    "endTime": "11:00 PM",
    "isPrivate": false,
    "published": true,
    "eventLink": "https://www.facebook.com/events/715141581162906/",
    "clientId": "c1f8e6d0-4a2b-4c5d-8e9f-1a2b3c4d5e6f",
    "setlist": "Riverbillies1-17.json",
    "itinerary": "Load-in: 6:00\nSet 1: 8:00 - 8:50\nSet 2: 9:05 - 9:55\nSet 3: 10:10 - 11:00",
    "personnel": [
      "Anthony",
      "Tom",
      "Lester",
      "Shelley",
      "Kelsey"
    ],
    "eventHandler": "Anthony",
    "payout": 750
  },
  {
    "id": "2cd3bad1-5321-43e2-970f-19e53e0ef5a4",
    "date": "2/20/2026",
    "venue": "Riverbillies",
    "city": "Gibraltar",
    "state": "MI",
    "startTime": "8:00 PM",
    "endTime": "11:00 PM",
    "isPrivate": false,
    "eventHandler": "Anthony",
    "published": true,
    "eventLink": "https://fb.me/e/5s4sMg2kh",
    "clientId": "c1f8e6d0-4a2b-4c5d-8e9f-1a2b3c4d5e6f",
    "itinerary": "Load-in: 6:00\nSet 1: 8:00 - 8:50\nSet 2: 9:05 - 9:55\nSet 3: 10:10 - 11:00",
    "personnel": [
      "Anthony",
      "Tom",
      "Lester",
      "David",
      "Shelley"
    ],
    "payout": 750
  },
  {
    "id": "e992c3fd-33d3-4967-8156-0f2591d635b2",
    "date": "2/27/2026",
    "venue": "Hell Saloon",
    "city": "Pinckney",
    "state": "MI",
    "published": true,
    "startTime": "8:00 PM",
    "endTime": "12:00 AM",
    "isPrivate": false,
    "eventHandler": "Anthony",
    "eventLink": "https://fb.me/e/8THzX8Ay3",
    "clientId": "f7a8b9c0-0d1e-4f2a-4b3c-7d8e9f0a1b2c",
    "itinerary": "Load-in: 6:00\nSet 1: 8:00 - 8:50\nSet 2: 9:05 - 9:55\nSet 3: 10:10 - 11:00\nSet 4: 11:10 - 12midnight",
    "personnel": [
      "Anthony",
      "Tom",
      "Lester",
      "David",
      "Shelley"
    ],
    "payout": 800
  },
  {
    "id": "5e32afdf-d92c-4b00-bdda-5729e2c765c3",
    "date": "3/14/2026",
    "venue": "Riverbillies",
    "city": "Gibraltar",
    "state": "MI",
    "published": true,
    "startTime": "8:00 PM",
    "endTime": "11:00 PM",
    "isPrivate": false,
    "eventHandler": "Anthony",
    "eventLink": "https://www.facebook.com/share/1DcNd8pWn7/",
    "clientId": "c1f8e6d0-4a2b-4c5d-8e9f-1a2b3c4d5e6f",
    "itinerary": "Load-in: 6:00\nSet 1: 8:00 - 8:50\nSet 2: 9:05 - 9:55\nSet 3: 10:10 - 11:00",
    "personnel": [
      "Anthony",
      "Tom",
      "Lester",
      "David",
      "Shelley"
    ],
    "payout": 750
  },
  {
    "id": "8fdd07f7-29db-485e-9bbe-b3d41df5bbf8",
    "date": "4/18/2026",
    "venue": "Hell Saloon",
    "city": "Pinckney",
    "published": true,
    "state": "MI",
    "startTime": "8:00 PM",
    "endTime": "12:00 AM",
    "isPrivate": false,
    "eventHandler": "Anthony",
    "eventLink": "https://www.facebook.com/share/17gL1j57xs/",
    "clientId": "f7a8b9c0-0d1e-4f2a-4b3c-7d8e9f0a1b2c",
    "itinerary": "Load-in: 6:00\nSet 1: 8:00 - 8:50\nSet 2: 9:05 - 9:55\nSet 3: 10:10 - 11:00\nSet 4: 11:10 - 12midnight",
    "personnel": [
      "Anthony",
      "Tom",
      "Lester",
      "David",
      "Shelley"
    ],
    "payout": 800
  },
  {
    "id": "797b8978-7ea9-4a51-a042-7e370d386cc1",
    "date": "5/9/2026",
    "venue": "Uncle Lyle's Tavern",
    "city": "Dundee",
    "state": "MI",
    "published": true,
    "startTime": "8:00 PM",
    "endTime": "11:00 PM",
    "isPrivate": false,
    "eventHandler": "Anthony",
    "eventLink": "https://fb.me/e/5qG9tajDK",
    "clientId": "b9c0d1e2-2f3a-4b4c-6d5e-9f0a1b2c3d4e",
    "personnel": [
      "Anthony",
      "Tom",
      "Lester",
      "Shelley",
      "Kelsey"
    ]
  },
  {
    "id": "d5132e25-4e51-48da-9c97-b2e9d2d1fc5c",
    "date": "6/6/2026",
    "venue": "The Sandtrap",
    "city": "Riverview",
    "published": true,
    "state": "MI",
    "startTime": "8:00 PM",
    "endTime": "11:00 PM",
    "isPrivate": false,
    "eventHandler": "Anthony",
    "eventLink": "https://www.facebook.com/share/1CNXEzQEpZ/",
    "clientId": "c0d1e2f3-3a4b-4c5d-7e6f-0a1b2c3d4e5f",
    "personnel": [
      "Anthony",
      "Tom",
      "Lester",
      "David",
      "Shelley"
    ],
    "payout": 1000
  },
  {
    "id": "b16b2108-0b49-42ff-a665-b0343d46f4cf",
    "date": "6/14/2026",
    "published": true,
    "venue": "Graduation Party",
    "city": "",
    "state": "",
    "startTime": "12:00 AM",
    "endTime": "",
    "isPrivate": true,
    "eventHandler": "Anthony",
    "eventLink": "",
    "clientId": "e2f3a4b5-5c6d-4e7f-9a8b-2c3d4e5f6a7b",
    "quote": "Graduation_Party_6-14-2026.json"
  },
  {
    "id": "52628fdf-04d9-4d36-8faa-984818833c6e",
    "date": "7/17/2026",
    "published": true,
    "venue": "SandBar Grille",
    "city": "LaSalle",
    "state": "MI",
    "startTime": "8:00 PM",
    "endTime": "12:00 AM",
    "isPrivate": false,
    "eventHandler": "Anthony",
    "eventLink": "https://fb.me/e/48LpTC6Um",
    "clientId": "a2b3c4d5-5e6f-4a7b-9c8d-2e3f4a5b6c7d",
    "personnel": [
      "Anthony",
      "Tom",
      "Lester",
      "David",
      "Shelley"
    ]
  },
  {
    "id": "87558bfd-2dad-4b5b-a040-c0a8f44fb092",
    "date": "8/8/2026",
    "venue": "Bier Stube Bar and Grille",
    "city": "Toledo",
    "state": "OH",
    "startTime": "8:00 PM",
    "endTime": "11:00 PM",
    "published": true,
    "isPrivate": false,
    "eventHandler": "Anthony",
    "eventLink": "https://fb.me/e/5zTpW4P98",
    "clientId": "d1e2f3a4-4b5c-4d6e-8f7a-1b2c3d4e5f6a",
    "personnel": [
      "Anthony",
      "Tom",
      "Lester",
      "David",
      "Shelley"
    ],
    "payout": 800
  },
  {
    "id": "d592e318-c084-4395-bbe0-7a4196848ed6",
    "date": "8/28/2026",
    "venue": "SandBar Grille",
    "city": "LaSalle",
    "published": true,
    "state": "MI",
    "startTime": "8:00 PM",
    "endTime": "12:00 AM",
    "isPrivate": false,
    "eventHandler": "Anthony",
    "eventLink": "https://fb.me/e/3YQf98oCO",
    "clientId": "a2b3c4d5-5e6f-4a7b-9c8d-2e3f4a5b6c7d",
    "personnel": [
      "Anthony",
      "Tom",
      "Lester",
      "David",
      "Shelley"
    ]
  }
]