[
  { "title": "Sex On Fire", "genre": "Rock" },
  { "title": "Treasure", "genre": "Pop" },
  { "title": "Beer Never Broke My Heart", "genre": "Country" },
  { "title": "Ain't No Sunshine", "genre": "Soul" },
  { "title": "MmmBop", "genre": "Pop" },
  { "title": "Don't Stop Believin'", "genre": "Rock" },
  { "title": "Wagon Wheel", "genre": "Country" },
  { "title": "Toxic", "genre": "Pop" },
  { "title": "Play That Funky Music", "genre": "Soul" },
  { "title": "I Want It That Way", "genre": "Pop" },
  { "title": "Redneck Woman", "genre": "Country" },
  { "title": "Semi-Charmed Life", "genre": "Rock" },
  { "title": "Flowers", "genre": "Pop" },
  { "title": "Tennessee Whiskey", "genre": "Country" },
  { "title": "Smooth", "genre": "Rock" },
  { "title": "Valerie", "genre": "Soul" },
  { "title": "Save a Horse (Ride a Cowboy)", "genre": "Country" },
  { "title": "Levitating", "genre": "Pop" },
  { "title": "My Own Worst Enemy", "genre": "Rock" },
  { "title": "Chicken Fried", "genre": "Country" },
  { "title": "Superstition", "genre": "Soul" },
  { "title": "Dancing in the Moonlight", "genre": "Pop" },
  { "title": "Before He Cheats", "genre": "Country" },
  { "title": "Pony", "genre": "R&B" },
  { "title": "Mr. Brightside", "genre": "Rock" },
  { "title": "I Had Some Help", "genre": "Country" },
  { "title": "Uptown Funk", "genre": "Pop" },
  { "title": "Dreams", "genre": "Rock" },
  { "title": "Neon Moon", "genre": "Country" },
  { "title": "Good as Hell", "genre": "Pop" },
  { "title": "Sweetness", "genre": "Rock" },
  { "title": "Any Man Of Mine", "genre": "Country" },
  { "title": "24K Magic", "genre": "Pop" },
  { "title": "Interstate Love Song", "genre": "Rock" },
  { "title": "Fishin' In The Dark", "genre": "Country" },
  { "title": "Lose Control", "genre": "Soul" },
  { "title": "Rock & Roll", "genre": "Rock" },
  { "title": "Man! I Feel Like a Woman!", "genre": "Country" },
  { "title": "Espresso", "genre": "Pop" },
  { "title": "Ain't It Fun", "genre": "Rock" },
  { "title": "Friends in Low Places", "genre": "Country" },
  { "title": "The Way You Make Me Feel", "genre": "Pop" },
  { "title": "Sugar, We're Goin Down", "genre": "Rock" },
  { "title": "Brown Eyed Lover", "genre": "Soul" },
  { "title": "Sin Wagon", "genre": "Country" },
  { "title": "Watermelon Sugar", "genre": "Pop" },
  { "title": "Aeroplane", "genre": "Rock" },
  { "title": "December 1963 (Oh, What a Night)", "genre": "Soul" },
  { "title": "Country Girl", "genre": "Country" },
  { "title": "I Wanna Dance With Somebody", "genre": "Pop" },
  { "title": "Higher", "genre": "Rock" },
  { "title": "Signed, Sealed, Delivered", "genre": "Soul" },
  { "title": "Boot Scootin' Boogie", "genre": "Country" },
  { "title": "Don't Start Now", "genre": "Pop" },
  { "title": "Mary Jane's Last Dance", "genre": "Rock" },
  { "title": "Tipsy", "genre": "R&B" },
  { "title": "As Good As I Once Was", "genre": "Country" },
  { "title": "About Damn Time", "genre": "Pop" },
  { "title": "Something To Talk About", "genre": "Rock" },
  { "title": "Isn't She Lovely", "genre": "Soul" },
  { "title": "You Look Like You Love Me", "genre": "Country" },
  { "title": "Juice", "genre": "Pop" },
  { "title": "Drive", "genre": "Rock" },
  { "title": "September", "genre": "Soul" },
  { "title": "Sparks Fly", "genre": "Country" },
  { "title": "Shut Up and Dance", "genre": "Pop" },
  { "title": "All the Small Things", "genre": "Rock" },
  { "title": "Need a Favor", "genre": "Country" },
  { "title": "I Feel It Coming", "genre": "Pop" },
  { "title": "Wish I Knew You", "genre": "Rock" },
  { "title": "Pink Pony Club", "genre": "Pop" },
  { "title": "Dead or Alive", "genre": "Rock" },
  { "title": "Unholy", "genre": "Pop" },
  { "title": "Sweet Emotion", "genre": "Rock" },
  { "title": "Killing In the Name", "genre": "Rock" }
]
